gpg_vault/__init__.py
gpg_vault/client.py
gpg_vault/command.py
gpg_vault/config.py
gpg_vault/crypto.py
gpg_vault/errors.py
gpg_vault/file.py
gpg_vault/log.py
gpg_vault/server.py
gpg_vault/utils.py
gpg_vault/vault.py
gpg_vault-1.5.1.data/scripts/gpg-vault-server
gpg_vault-1.5.1.data/scripts/vcat
gpg_vault-1.5.1.data/scripts/vclear
gpg_vault-1.5.1.data/scripts/vedit
gpg_vault-1.5.1.data/scripts/vencrypt
gpg_vault-1.5.1.data/scripts/vopen
gpg_vault-1.5.1.data/scripts/vreencrypt
gpg_vault-1.5.1.dist-info/LICENSE
gpg_vault-1.5.1.dist-info/METADATA
gpg_vault-1.5.1.dist-info/WHEEL
gpg_vault-1.5.1.dist-info/top_level.txt
gpg_vault-1.5.1.dist-info/RECORD
